pybats_detection/__init__.py
pybats_detection/intervention.py
pybats_detection/loader.py
pybats_detection/monitor.py
pybats_detection/random_dlm.py
pybats_detection/smooth.py
pybats_detection/utils.py
pybats_detection/data/air_passengers.csv
pybats_detection/data/cp6__west_harrison.csv
pybats_detection/data/pole_market_share.csv
pybats_detection/data/telephone_calls__pankratz.csv
pybats_detection-0.2.1.dist-info/LICENSE.md
pybats_detection-0.2.1.dist-info/METADATA
pybats_detection-0.2.1.dist-info/WHEEL
pybats_detection-0.2.1.dist-info/top_level.txt
pybats_detection-0.2.1.dist-info/RECORD
