Metadata-Version: 2.1
Name: pybats-detection
Version: 0.2.1
Summary: Tools for outlier and structural changes detection in time series analysis using Bayesian Dynamic Linear Model.
Home-page: https://github.com/Murabei-OpenSource-Codes/pybats-detection
Author: André Menezes and Eduardo Pinheiro
Author-email: andrefelipemaringa@gmail.com
License: UNKNOWN
Platform: UNKNOWN
Classifier: Programming Language :: Python :: 3
Classifier: License :: OSI Approved :: Apache Software License
Classifier: Operating System :: OS Independent
Requires-Python: >=3.6
